guardeye_python_sdk/__init__.py
guardeye_python_sdk/link.proto
guardeye_python_sdk/link_pb2.py
guardeye_python_sdk/link_pb2_grpc.py
guardeye_python_sdk-0.1.0.dist-info/METADATA
guardeye_python_sdk-0.1.0.dist-info/WHEEL
guardeye_python_sdk-0.1.0.dist-info/RECORD
