Metadata-Version: 2.1
Name: guardeye-python-sdk
Version: 0.1.0
Summary: 
Author: shawn
Author-email: shawnsiu@outlook.com
Requires-Python: >=3.9,<4.0
Classifier: Programming Language :: Python :: 3
Classifier: Programming Language :: Python :: 3.9
Classifier: Programming Language :: Python :: 3.10
Classifier: Programming Language :: Python :: 3.11
Classifier: Programming Language :: Python :: 3.12
Classifier: Programming Language :: Python :: 3.13
Requires-Dist: grpcio (>=1.71.0,<2.0.0)
Requires-Dist: grpcio-tools (>=1.71.0,<2.0.0)
